LICENSE
MANIFEST.in
README.md
pyproject.toml
setup.cfg
setup.py
cvd_risk_scores.egg-info/PKG-INFO
cvd_risk_scores.egg-info/SOURCES.txt
cvd_risk_scores.egg-info/dependency_links.txt
cvd_risk_scores.egg-info/requires.txt
cvd_risk_scores.egg-info/top_level.txt
src/cvd_risk_scores/__init__.py
src/cvd_risk_scores/modules/__init__.py
src/cvd_risk_scores/modules/risk_models.py
src/cvd_risk_scores/modules/templates.py
src/cvd_risk_scores/modules/typings.py
src/cvd_risk_scores/modules/utils.py