Metadata-Version: 2.1
Name: cvd-risk-scores
Version: 1.0.1
Summary: A Python package for computing cardiovascular disease risk using clinically validated models.
Home-page: https://github.com/francescopisu/CVD-risk-scores
Author: francesco-pisu
Author-email: fra.pisu1@gmail.com
License: MIT
Platform: UNKNOWN
Classifier: Development Status :: 2 - Pre-Alpha
Classifier: Intended Audience :: Science/Research
Classifier: Topic :: Scientific/Engineering :: Medical Science Apps.
Classifier: License :: OSI Approved :: MIT License
Classifier: Programming Language :: Python :: 3
Classifier: Programming Language :: Python :: 3.7
Classifier: Programming Language :: Python :: 3.8
Classifier: Programming Language :: Python :: 3.9
Requires-Python: >=3.7,<3.10
